mc_pack_generator/__init__.py
mc_pack_generator/main.py
mc_pack_generator-0.1.3.dist-info/METADATA
mc_pack_generator-0.1.3.dist-info/WHEEL
mc_pack_generator-0.1.3.dist-info/entry_points.txt
mc_pack_generator-0.1.3.dist-info/top_level.txt
mc_pack_generator-0.1.3.dist-info/RECORD
