Metadata-Version: 2.4
Name: mc-pack-generator
Version: 0.1.3
Summary: Gerador de pacotes para Minecraft Bedrock (Behavior, Resource, Skin)
Author: Seu Nome
Requires-Python: >=3.6
Dynamic: author
Dynamic: description
Dynamic: description-content-type
Dynamic: requires-python
Dynamic: summary
